emr_helper/__init__.py
emr_helper/cluster.py
emr_helper/fleet.py
emr_helper/step.py
emr_helper-1.0.0.dist-info/LICENSE
emr_helper-1.0.0.dist-info/METADATA
emr_helper-1.0.0.dist-info/WHEEL
emr_helper-1.0.0.dist-info/top_level.txt
emr_helper-1.0.0.dist-info/RECORD
