Metadata-Version: 2.1
Name: emr-helper
Version: 1.0.0
Summary: Library to manage AWS EMR clusters.
Home-page: https://github.com/JevyanJ/emr-helper
Author: JevyanJ
Author-email: jjrg184@gmail.com
License: UNKNOWN
Platform: UNKNOWN
Classifier: Programming Language :: Python :: 3
Classifier: License :: OSI Approved :: MIT License
Classifier: Operating System :: OS Independent
Requires-Python: >=3.6
